[{"_id":"637e71ffe94ec5bbec644215","gender":"female","name":"Alexander Madden","contact":"(862) 500-3347","address":"461 Micieli Place, Outlook, Alaska, 4140","picture":"http://placehold.it/32x32"},{"_id":"637e71ff5f7d5f8dfab5b35f","gender":"male","name":"Conrad Hamilton","contact":"(961) 417-3959","address":"652 Vista Place, Cumberland, Vermont, 9104","picture":"http://placehold.it/32x32"},{"_id":"637e71ff8f9417f5e1e919cb","gender":"male","name":"Beulah Christensen","contact":"(887) 525-3908","address":"796 Calder Place, Marienthal, Oregon, 7415","picture":"http://placehold.it/32x32"},{"_id":"637e71ff68e3575330a88725","gender":"female","name":"Mooney Wilcox","contact":"(879) 489-2561","address":"593 Jamaica Avenue, Whitestone, Maryland, 3601","picture":"http://placehold.it/32x32"},{"_id":"637e71ff38f55c84a84a85e7","gender":"male","name":"Salazar Pope","contact":"(895) 578-2098","address":"619 Woodside Avenue, Wheaton, Rhode Island, 6234","picture":"http://placehold.it/32x32"},{"_id":"637e71ff0366f568d33d97a2","gender":"male","name":"Austin Chan","contact":"(958) 600-3134","address":"344 Interborough Parkway, Frizzleburg, Texas, 5371","picture":"http://placehold.it/32x32"},{"_id":"637e71ff8dcc5ffec77d4d50","gender":"male","name":"Humphrey Bass","contact":"(969) 465-3099","address":"465 Gerry Street, Leola, American Samoa, 3532","picture":"http://placehold.it/32x32"},{"_id":"637e71ff96d9888e4969822e","gender":"male","name":"Cooley Vang","contact":"(988) 400-2780","address":"956 Raleigh Place, Disautel, New Mexico, 6246","picture":"http://placehold.it/32x32"},{"_id":"637e71ff36d9ec0123207d40","gender":"male","name":"Amalia Rojas","contact":"(975) 465-3362","address":"592 Humboldt Street, Breinigsville, Mississippi, 9602","picture":"http://placehold.it/32x32"},{"_id":"637e71ffa25b38770f4d3d84","gender":"female","name":"Medina Dickson","contact":"(955) 599-3090","address":"184 Tehama Street, Robinson, Wyoming, 471","picture":"http://placehold.it/32x32"},{"_id":"637e71ff95004c709f60e49d","gender":"male","name":"House Wise","contact":"(992) 514-2713","address":"686 Eldert Street, Romeville, Delaware, 7656","picture":"http://placehold.it/32x32"},{"_id":"637e71ffe6f868cb7c9bcdc0","gender":"male","name":"Sawyer Ferguson","contact":"(867) 507-2713","address":"933 Virginia Place, Rosewood, North Carolina, 9716","picture":"http://placehold.it/32x32"},{"_id":"637e71ffef686f3748ba625c","gender":"male","name":"Barrera Leblanc","contact":"(946) 525-2813","address":"598 Troutman Street, Hiwasse, Pennsylvania, 900","picture":"http://placehold.it/32x32"},{"_id":"637e71fff17c6b2a6628dc34","gender":"male","name":"Cameron Dennis","contact":"(888) 456-3360","address":"372 Neptune Court, Datil, Oklahoma, 2213","picture":"http://placehold.it/32x32"},{"_id":"637e71ffec4ab9e9dfa23705","gender":"male","name":"Charlotte Newton","contact":"(966) 527-2920","address":"168 Beard Street, Groveville, Palau, 7346","picture":"http://placehold.it/32x32"},{"_id":"637e71ff66568f2d140c5e51","gender":"female","name":"Gillespie Harrison","contact":"(958) 451-2031","address":"333 Lloyd Court, Weedville, Kansas, 3350","picture":"http://placehold.it/32x32"},{"_id":"637e71ff35de080ef667dce8","gender":"male","name":"Bettie George","contact":"(931) 557-2427","address":"804 Diamond Street, Joes, South Dakota, 9074","picture":"http://placehold.it/32x32"},{"_id":"637e71ffa9ce53983736d13e","gender":"female","name":"Sykes Fuller","contact":"(946) 550-2441","address":"972 Eagle Street, Roosevelt, Arizona, 7324","picture":"http://placehold.it/32x32"},{"_id":"637e71ffebae4b0bbb30204e","gender":"male","name":"Kelley Cline","contact":"(924) 505-3981","address":"263 Auburn Place, Germanton, Virginia, 6486","picture":"http://placehold.it/32x32"},{"_id":"637e71ff967f51ce7f35bf9c","gender":"female","name":"Cecelia Eaton","contact":"(840) 468-3642","address":"481 Gerritsen Avenue, Curtice, Florida, 9606","picture":"http://placehold.it/32x32"},{"_id":"123abc","gender":"male","name":"Habib","contact":"(433) 400-6433","address":"221 B, Baker Street, London","picture":"http://placehold.it/32x32"}]